{
    "WeatherForecasts": [
        {
            "location": {
                "lat": 13.7426,
                "lon": 100.4965
            },
            "forecasts": [
                {
                    "time": "2026-04-25T07:00:00+07:00",
                    "data": {
                        "cond": 3,
                        "rain": 0,
                        "rh": 84.48,
                        "slp": 1009.94,
                        "tc": 28.82,
                        "wd10m": 193.31,
                        "ws10m": 2.12
                    }
                },
                {
                    "time": "2026-04-25T08:00:00+07:00",
                    "data": {
                        "cond": 4,
                        "rain": 0,
                        "rh": 76.53,
                        "slp": 1010.65,
                        "tc": 29.34,
                        "wd10m": 173.81,
                        "ws10m": 1.75
                    }
                },
                {
                    "time": "2026-04-25T09:00:00+07:00",
                    "data": {
                        "cond": 4,
                        "rain": 0,
                        "rh": 54.04,
                        "slp": 1011.54,
                        "tc": 28.85,
                        "wd10m": 147.07,
                        "ws10m": 4.38
                    }
                },
                {
                    "time": "2026-04-25T10:00:00+07:00",
                    "data": {
                        "cond": 4,
                        "rain": 0,
                        "rh": 60.27,
                        "slp": 1012.13,
                        "tc": 28.22,
                        "wd10m": 166.06,
                        "ws10m": 5.77
                    }
                },
                {
                    "time": "2026-04-25T11:00:00+07:00",
                    "data": {
                        "cond": 4,
                        "rain": 0,
                        "rh": 47.68,
                        "slp": 1012.06,
                        "tc": 33.83,
                        "wd10m": 174.13,
                        "ws10m": 0.86
                    }
                },
                {
                    "time": "2026-04-25T12:00:00+07:00",
                    "data": {
                        "cond": 3,
                        "rain": 0,
                        "rh": 44.4,
                        "slp": 1010.65,
                        "tc": 31.35,
                        "wd10m": 167.7,
                        "ws10m": 5.91
                    }
                },
                {
                    "time": "2026-04-25T13:00:00+07:00",
                    "data": {
                        "cond": 3,
                        "rain": 0,
                        "rh": 54.49,
                        "slp": 1009.77,
                        "tc": 33.05,
                        "wd10m": 176.36,
                        "ws10m": 6.92
                    }
                },
                {
                    "time": "2026-04-25T14:00:00+07:00",
                    "data": {
                        "cond": 1,
                        "rain": 0,
                        "rh": 56.29,
                        "slp": 1008.4,
                        "tc": 33.56,
                        "wd10m": 191.28,
                        "ws10m": 8.88
                    }
                },
                {
                    "time": "2026-04-25T15:00:00+07:00",
                    "data": {
                        "cond": 2,
                        "rain": 0,
                        "rh": 54.79,
                        "slp": 1007.13,
                        "tc": 33.73,
                        "wd10m": 195.44,
                        "ws10m": 9.84
                    }
                },
                {
                    "time": "2026-04-25T16:00:00+07:00",
                    "data": {
                        "cond": 1,
                        "rain": 0,
                        "rh": 58.93,
                        "slp": 1006.69,
                        "tc": 33.55,
                        "wd10m": 188.12,
                        "ws10m": 11.31
                    }
                },
                {
                    "time": "2026-04-25T17:00:00+07:00",
                    "data": {
                        "cond": 1,
                        "rain": 0,
                        "rh": 60,
                        "slp": 1006.26,
                        "tc": 32.77,
                        "wd10m": 193.56,
                        "ws10m": 9.47
                    }
                },
                {
                    "time": "2026-04-25T18:00:00+07:00",
                    "data": {
                        "cond": 1,
                        "rain": 0,
                        "rh": 62.32,
                        "slp": 1007.49,
                        "tc": 32.14,
                        "wd10m": 189.35,
                        "ws10m": 8.31
                    }
                },
                {
                    "time": "2026-04-25T19:00:00+07:00",
                    "data": {
                        "cond": 1,
                        "rain": 0,
                        "rh": 58.49,
                        "slp": 1007.91,
                        "tc": 32.53,
                        "wd10m": 193.8,
                        "ws10m": 6.71
                    }
                },
                {
                    "time": "2026-04-25T20:00:00+07:00",
                    "data": {
                        "cond": 2,
                        "rain": 0,
                        "rh": 73.96,
                        "slp": 1008.68,
                        "tc": 30.39,
                        "wd10m": 177.31,
                        "ws10m": 6.26
                    }
                },
                {
                    "time": "2026-04-25T21:00:00+07:00",
                    "data": {
                        "cond": 1,
                        "rain": 0,
                        "rh": 74.16,
                        "slp": 1009.22,
                        "tc": 30.26,
                        "wd10m": 187.01,
                        "ws10m": 6.4
                    }
                },
                {
                    "time": "2026-04-25T22:00:00+07:00",
                    "data": {
                        "cond": 2,
                        "rain": 0,
                        "rh": 67.65,
                        "slp": 1009.55,
                        "tc": 30.88,
                        "wd10m": 186.79,
                        "ws10m": 5.28
                    }
                },
                {
                    "time": "2026-04-25T23:00:00+07:00",
                    "data": {
                        "cond": 1,
                        "rain": 0,
                        "rh": 77.28,
                        "slp": 1009.91,
                        "tc": 29.76,
                        "wd10m": 181.97,
                        "ws10m": 5.28
                    }
                },
                {
                    "time": "2026-04-26T00:00:00+07:00",
                    "data": {
                        "cond": 4,
                        "rain": 0,
                        "rh": 10.11,
                        "slp": 1009.56,
                        "tc": 26.54,
                        "wd10m": 229.07,
                        "ws10m": 6.17
                    }
                },
                {
                    "time": "2026-04-26T01:00:00+07:00",
                    "data": {
                        "cond": 3,
                        "rain": 0,
                        "rh": 46.51,
                        "slp": 1008.8,
                        "tc": 30.53,
                        "wd10m": 188.03,
                        "ws10m": 3.55
                    }
                },
                {
                    "time": "2026-04-26T02:00:00+07:00",
                    "data": {
                        "cond": 3,
                        "rain": 0,
                        "rh": 63.65,
                        "slp": 1008.74,
                        "tc": 28.93,
                        "wd10m": 217.38,
                        "ws10m": 3.81
                    }
                },
                {
                    "time": "2026-04-26T03:00:00+07:00",
                    "data": {
                        "cond": 3,
                        "rain": 0,
                        "rh": 47.94,
                        "slp": 1008.44,
                        "tc": 29.08,
                        "wd10m": 222.06,
                        "ws10m": 3.14
                    }
                },
                {
                    "time": "2026-04-26T04:00:00+07:00",
                    "data": {
                        "cond": 5,
                        "rain": 0.1,
                        "rh": 73.05,
                        "slp": 1008.29,
                        "tc": 26.84,
                        "wd10m": 243.44,
                        "ws10m": 2.11
                    }
                },
                {
                    "time": "2026-04-26T05:00:00+07:00",
                    "data": {
                        "cond": 3,
                        "rain": 0,
                        "rh": 58.4,
                        "slp": 1008.47,
                        "tc": 29.22,
                        "wd10m": 285.22,
                        "ws10m": 0.29
                    }
                },
                {
                    "time": "2026-04-26T06:00:00+07:00",
                    "data": {
                        "cond": 3,
                        "rain": 0,
                        "rh": 68.87,
                        "slp": 1009.61,
                        "tc": 28.04,
                        "wd10m": 161.93,
                        "ws10m": 1.83
                    }
                }
            ]
        }
    ]
}